odoo/addons/ebill_postfinance/README.rst
odoo/addons/ebill_postfinance/__init__.py
odoo/addons/ebill_postfinance/__manifest__.py
odoo/addons/ebill_postfinance/data/ir_cron.xml
odoo/addons/ebill_postfinance/data/mail_activity_type.xml
odoo/addons/ebill_postfinance/data/transmit.method.xml
odoo/addons/ebill_postfinance/i18n/ebill_postfinance.pot
odoo/addons/ebill_postfinance/messages/invoice-2003A.jinja
odoo/addons/ebill_postfinance/messages/invoice-yellowbill.jinja
odoo/addons/ebill_postfinance/messages/ybInvoice_V2.0.4.xsd
odoo/addons/ebill_postfinance/models/__init__.py
odoo/addons/ebill_postfinance/models/account_move.py
odoo/addons/ebill_postfinance/models/account_move_line.py
odoo/addons/ebill_postfinance/models/ebill_payment_contract.py
odoo/addons/ebill_postfinance/models/ebill_postfinance_invoice_message.py
odoo/addons/ebill_postfinance/models/ebill_postfinance_service.py
odoo/addons/ebill_postfinance/models/sale_order.py
odoo/addons/ebill_postfinance/readme/CONFIGURE.md
odoo/addons/ebill_postfinance/readme/CONTRIBUTORS.md
odoo/addons/ebill_postfinance/readme/DESCRIPTION.md
odoo/addons/ebill_postfinance/readme/INSTALL.md
odoo/addons/ebill_postfinance/readme/ROADMAP.md
odoo/addons/ebill_postfinance/readme/USAGE.md
odoo/addons/ebill_postfinance/security/ir.model.access.csv
odoo/addons/ebill_postfinance/static/description/icon.png
odoo/addons/ebill_postfinance/static/description/index.html
odoo/addons/ebill_postfinance/tests/__init__.py
odoo/addons/ebill_postfinance/tests/common.py
odoo/addons/ebill_postfinance/tests/test_account_move.py
odoo/addons/ebill_postfinance/tests/test_ebill_postfinance.py
odoo/addons/ebill_postfinance/tests/test_ebill_postfinance_message_yb.py
odoo/addons/ebill_postfinance/tests/test_ebill_postfinance_message_yb_creditnote.py
odoo/addons/ebill_postfinance/tests/fixtures/cassettes/test_ping_service.yaml
odoo/addons/ebill_postfinance/tests/fixtures/cassettes/test_search_invoices.yaml
odoo_addon_ebill_postfinance-18.0.1.2.0.8.dist-info/METADATA
odoo_addon_ebill_postfinance-18.0.1.2.0.8.dist-info/WHEEL
odoo_addon_ebill_postfinance-18.0.1.2.0.8.dist-info/top_level.txt
odoo_addon_ebill_postfinance-18.0.1.2.0.8.dist-info/RECORD
