Metadata-Version: 2.1
Name: odoo-addon-ebill_postfinance
Version: 18.0.1.2.0.8
Requires-Python: >=3.10
Requires-Dist: ebilling_postfinance
Requires-Dist: odoo-addon-account_invoice_export==18.0.*
Requires-Dist: odoo-addon-base_ebill_payment_contract==18.0.*
Requires-Dist: odoo==18.0.*
Requires-Dist: zeep
Summary: Postfinance eBill integration
Home-page: https://github.com/OCA/l10n-switzerland
License: AGPL-3
Author: Camptocamp,Odoo Community Association (OCA)
Author-email: support@odoo-community.org
Classifier: Programming Language :: Python
Classifier: Framework :: Odoo
Classifier: Framework :: Odoo :: 18.0
Classifier: License :: OSI Approved :: GNU Affero General Public License v3
